{"fur10_ELECTRIC": {"url": "./fur/fur10_ELECTRIC.png", "weight": 0, "supply": 0}, "fur10_ELECTRIC_T": {"url": "./fur/fur10_ELECTRIC_T.png", "weight": 0, "supply": 0}, "fur11_ZOMBIE": {"url": "./fur/fur11_ZOMBIE.png", "weight": 0, "supply": 0}, "fur11_ZOMBIE_T": {"url": "./fur/fur11_ZOMBIE_T.png", "weight": 0, "supply": 0}, "fur12_ALIEN": {"url": "./fur/fur12_ALIEN.png", "weight": 0, "supply": 0}, "fur12_ALIEN_T": {"url": "./fur/fur12_ALIEN_T.png", "weight": 0, "supply": 0}, "fur13_BROWN": {"url": "./fur/fur13_BROWN.png", "weight": 0, "supply": 0}, "fur13_BROWN_T": {"url": "./fur/fur13_BROWN_T.png", "weight": 0, "supply": 0}, "fur14_RED": {"url": "./fur/fur14_RED.png", "weight": 0, "supply": 0}, "fur14_RED_T": {"url": "./fur/fur14_RED_T.png", "weight": 0, "supply": 0}, "fur15_GHOST": {"url": "./fur/fur15_GHOST.png", "weight": 0, "supply": 0}, "fur15_GHOST_T": {"url": "./fur/fur15_GHOST_T.png", "weight": 0, "supply": 0}, "fur16_ROBOT": {"url": "./fur/fur16_ROBOT.png", "weight": 0, "supply": 0}, "fur16_ROBOT_T": {"url": "./fur/fur16_ROBOT_T.png", "weight": 0, "supply": 0}, "fur1_GOLD": {"url": "./fur/fur1_GOLD.png", "weight": 0, "supply": 0}, "fur1_GOLD_T": {"url": "./fur/fur1_GOLD_T.png", "weight": 0, "supply": 0}, "fur2_BLUE": {"url": "./fur/fur2_BLUE.png", "weight": 0, "supply": 0}, "fur2_BLUEpng": {"url": "./fur/fur2_BLUEpng.png", "weight": 0, "supply": 0}, "fur2_BLUE_T": {"url": "./fur/fur2_BLUE_T.png", "weight": 0, "supply": 0}, "fur3_SHINY": {"url": "./fur/fur3_SHINY.png", "weight": 0, "supply": 0}, "fur3_SHINY_T": {"url": "./fur/fur3_SHINY_T.png", "weight": 0, "supply": 0}, "fur4_BASIC": {"url": "./fur/fur4_BASIC.png", "weight": 0, "supply": 0}, "fur4_BASIC_T": {"url": "./fur/fur4_BASIC_T.png", "weight": 0, "supply": 0}, "fur5_RAINBOW": {"url": "./fur/fur5_RAINBOW.png", "weight": 0, "supply": 0}, "fur5_RAINBOW_T": {"url": "./fur/fur5_RAINBOW_T.png", "weight": 0, "supply": 0}, "fur6_BLACK": {"url": "./fur/fur6_BLACK.png", "weight": 0, "supply": 0}, "fur6_BLACK_T": {"url": "./fur/fur6_BLACK_T.png", "weight": 0, "supply": 0}, "fur7_ALBINOWHITE": {"url": "./fur/fur7_ALBINOWHITE.png", "weight": 0, "supply": 0}, "fur7_ALBINOWHITE_T": {"url": "./fur/fur7_ALBINOWHITE_T.png", "weight": 0, "supply": 0}, "fur8_ORANGE": {"url": "./fur/fur8_ORANGE.png", "weight": 0, "supply": 0}, "fur8_ORANGE_T": {"url": "./fur/fur8_ORANGE_T.png", "weight": 0, "supply": 0}, "fur9_NAKED": {"url": "./fur/fur9_NAKED.png", "weight": 0, "supply": 0}, "fur9_NAKED_T": {"url": "./fur/fur9_NAKED_T.png", "weight": 0, "supply": 0}}